mrc/__init__.py
mrc/_new.py
mrc/_version.py
mrc/lenses.py
mrc/mrc.py
mrc/py.typed
mrc-0.4.0.dist-info/METADATA
mrc-0.4.0.dist-info/WHEEL
mrc-0.4.0.dist-info/licenses/LICENSE
mrc-0.4.0.dist-info/RECORD
