Metadata-Version: 2.4
Name: mrc
Version: 0.4.0
Summary: Read and write .mrc and .dv (deltavision) image file format
Project-URL: Source Code, https://github.com/tlambert03/mrc
Author-email: Talley Lambert <talley.lambert@gmail.com>
License: BSD-3-Clause
License-File: LICENSE
Classifier: Development Status :: 4 - Beta
Classifier: License :: OSI Approved :: BSD License
Classifier: Programming Language :: Python :: 3
Classifier: Programming Language :: Python :: 3.9
Classifier: Programming Language :: Python :: 3.10
Classifier: Programming Language :: Python :: 3.11
Classifier: Programming Language :: Python :: 3.12
Classifier: Programming Language :: Python :: 3.13
Classifier: Programming Language :: Python :: 3.14
Requires-Python: >=3.9
Requires-Dist: numpy>=1.25.2
Requires-Dist: numpy>=1.26.0; python_version >= '3.12'
Requires-Dist: numpy>=2.1.0; python_version >= '3.13'
Requires-Dist: numpy>=2.3.2; python_version >= '3.14'
